{"job":{"type":"presubmit","job":"pull-test-dev-rerere","buildid":"1435534918833672192","prowjobid":"cd93baf3-1086-11ec-b16c-ce1ba41f5cf6","refs":{"org":"ti-community-infra","repo":"test-dev","repo_link":"https://github.com/ti-community-infra/test-dev","base_ref":"master","base_sha":"a2392951cc63d7b7b3ddea904a61fa96614cf2e0","base_link":"https://github.com/ti-community-infra/test-dev/commit/a2392951cc63d7b7b3ddea904a61fa96614cf2e0","pulls":[{"number":439,"author":"Mini256","sha":"fddb3f732d32006bd41a3289f2a5b5ec1f896475","title":"[Fixed #438] *: fix bug","link":"https://github.com/ti-community-infra/test-dev/pull/439","commit_link":"https://github.com/ti-community-infra/test-dev/pull/439/commits/fddb3f732d32006bd41a3289f2a5b5ec1f896475","author_link":"https://github.com/Mini256"}]},"decoration_config":{"utility_images":{"clonerefs":"gcr.io/k8s-prow/clonerefs:v20210827-98f54bde95","initupload":"gcr.io/k8s-prow/initupload:v20210827-98f54bde95","entrypoint":"gcr.io/k8s-prow/entrypoint:v20210827-98f54bde95","sidecar":"gcr.io/k8s-prow/sidecar:v20210827-98f54bde95"},"gcs_configuration":{"bucket":"gs://prow-dev-tidb-logs","path_strategy":"explicit"},"gcs_credentials_secret":"gcs-credentials"}},"options":{"retesting-branch":"try","retry":3,"require_contexts":{},"timeout":900000000000},"current_retry_times":1,"time":"2021-09-08T09:29:18.396595484Z"}